xonsh_rd_parser-1.7.0.dist-info/METADATA
xonsh_rd_parser-1.7.0.dist-info/WHEEL
xonsh_rd_parser-1.7.0.dist-info/licenses/LICENSE
xonsh_rd_parser.libs/libgcc_s-0366c7ba.so.1
xonsh_rd_parser/__init__.py
xonsh_rd_parser/__init__.pyi
xonsh_rd_parser/py.typed
xonsh_rd_parser/xonsh_rd_parser.cpython-313t-arm-linux-musleabihf.so
xonsh_rd_parser-1.7.0.dist-info/RECORD
