Metadata-Version: 2.4
Name: xonsh_rd_parser
Version: 1.7.0
Classifier: Programming Language :: Rust
Classifier: Programming Language :: Python :: Implementation :: CPython
Classifier: Programming Language :: Python :: Implementation :: PyPy
License-File: LICENSE
Summary: A Rust based, recursive descent parser for Xonsh
Requires-Python: >=3.10
